goc/__init__.py
goc/config.py
goc/goc.py
goc-0.6.2.dist-info/METADATA
goc-0.6.2.dist-info/WHEEL
goc-0.6.2.dist-info/entry_points.txt
goc-0.6.2.dist-info/RECORD
