Metadata-Version: 2.1
Name: goc
Version: 0.6.2
Summary: 
Home-page: https://github.com/djentleman/goc
Author: Todd Perry
Author-email: toddperry171@gmail.com
Requires-Python: >=3.8,<4.0
Classifier: Programming Language :: Python :: 3
Classifier: Programming Language :: Python :: 3.8
Classifier: Programming Language :: Python :: 3.9
Classifier: Programming Language :: Python :: 3.10
Classifier: Programming Language :: Python :: 3.11
Requires-Dist: click (>=8.1.7,<9.0.0)
Requires-Dist: openai (>=0.27.8,<0.28.0)
Requires-Dist: pyyaml (>=6.0.1,<7.0.0)
Project-URL: Repository, https://github.com/djentleman/goc
